de_utils_lolo_san/__init__.py
de_utils_lolo_san/cli.py
de_utils_lolo_san/main.py
de_utils_lolo_san-0.1.0.dist-info/METADATA
de_utils_lolo_san-0.1.0.dist-info/WHEEL
de_utils_lolo_san-0.1.0.dist-info/entry_points.txt
de_utils_lolo_san-0.1.0.dist-info/top_level.txt
de_utils_lolo_san-0.1.0.dist-info/RECORD
